README.md
setup.py
vicmiko/__init__.py
vicmiko/junos.py
vicmiko.egg-info/PKG-INFO
vicmiko.egg-info/SOURCES.txt
vicmiko.egg-info/dependency_links.txt
vicmiko.egg-info/requires.txt
vicmiko.egg-info/top_level.txt