Metadata-Version: 2.1
Name: vicmiko
Version: 0.1.0
Summary: Python library to interact with Junos devices. Based on jnpr-pyez and jsnapy
Home-page: https://github.com/Vicnz03/vicmiko
Author: Vic Chen
Author-email: vicnz03@hotmail.com
License: MIT
Platform: UNKNOWN
Classifier: License :: OSI Approved :: MIT License
Classifier: Programming Language :: Python :: 3
Classifier: Programming Language :: Python :: 3.6
Classifier: Programming Language :: Python :: 3.7
Classifier: Programming Language :: Python :: 3.8
